maestro/__init__.py
maestro/openai.py
maestro_python-1.0.4.dist-info/licenses/LICENSE
maestro_python-1.0.4.dist-info/METADATA
maestro_python-1.0.4.dist-info/WHEEL
maestro_python-1.0.4.dist-info/top_level.txt
maestro_python-1.0.4.dist-info/RECORD
