Metadata-Version: 2.4
Name: maestro-python
Version: 1.0.4
Summary: Client API proxy for TaskiAI's Maestro.
Author-email: Arda Tasci <arda.tasci@taski-ai.com>
Project-URL: Issues, https://github.com/TaskiAI/maestro-python/issues
Project-URL: Homepage, https://github.com/TaskiAI/maestro-python/
Requires-Python: >=3.10
License-File: LICENSE
Requires-Dist: httpx>=0.28.1
Dynamic: license-file
